cjson_tools/__init__.py
cjson_tools/_cjson_tools.cp38-win_amd64.pyd
cjson_tools-1.9.0.dist-info/LICENSE
cjson_tools-1.9.0.dist-info/METADATA
cjson_tools-1.9.0.dist-info/WHEEL
cjson_tools-1.9.0.dist-info/top_level.txt
cjson_tools-1.9.0.dist-info/RECORD
